[
  {
    "word": "after",
    "appLevel": "A2",
    "oxfordLevel": "A1"
  },
  {
    "word": "before",
    "appLevel": "A2",
    "oxfordLevel": "A1"
  },
  {
    "word": "best",
    "appLevel": "A2",
    "oxfordLevel": "A1"
  },
  {
    "word": "cover",
    "appLevel": "B1",
    "oxfordLevel": "A2"
  },
  {
    "word": "drive",
    "appLevel": "A2",
    "oxfordLevel": "A1"
  },
  {
    "word": "fish",
    "appLevel": "A2",
    "oxfordLevel": "A1"
  },
  {
    "word": "fly",
    "appLevel": "A2",
    "oxfordLevel": "A1"
  },
  {
    "word": "last",
    "appLevel": "A2",
    "oxfordLevel": "A1"
  },
  {
    "word": "licence",
    "appLevel": "C1",
    "oxfordLevel": "B2"
  },
  {
    "word": "neither",
    "appLevel": "B1",
    "oxfordLevel": "A2"
  },
  {
    "word": "net",
    "appLevel": "C1",
    "oxfordLevel": "B1"
  },
  {
    "word": "original",
    "appLevel": "B1",
    "oxfordLevel": "A2"
  },
  {
    "word": "plus",
    "appLevel": "B2",
    "oxfordLevel": "B1"
  },
  {
    "word": "programme",
    "appLevel": "A2",
    "oxfordLevel": "A1"
  },
  {
    "word": "progress",
    "appLevel": "B2",
    "oxfordLevel": "A2"
  },
  {
    "word": "project",
    "appLevel": "C1",
    "oxfordLevel": "A1"
  },
  {
    "word": "protest",
    "appLevel": "C1",
    "oxfordLevel": "B1"
  },
  {
    "word": "screen",
    "appLevel": "B2",
    "oxfordLevel": "A2"
  },
  {
    "word": "shape",
    "appLevel": "B2",
    "oxfordLevel": "A2"
  },
  {
    "word": "total",
    "appLevel": "C1",
    "oxfordLevel": "B1"
  },
  {
    "word": "view",
    "appLevel": "B1",
    "oxfordLevel": "A2"
  },
  {
    "word": "worse",
    "appLevel": "B2",
    "oxfordLevel": "A2"
  },
  {
    "word": "acid",
    "appLevel": "C1",
    "oxfordLevel": "B2"
  },
  {
    "word": "alien",
    "appLevel": "C1",
    "oxfordLevel": "B2"
  },
  {
    "word": "dynamic",
    "appLevel": "C1",
    "oxfordLevel": "B2"
  },
  {
    "word": "extract",
    "appLevel": "C1",
    "oxfordLevel": "B2"
  },
  {
    "word": "obesity",
    "appLevel": "C1",
    "oxfordLevel": "B2"
  },
  {
    "word": "publicity",
    "appLevel": "C1",
    "oxfordLevel": "B2"
  },
  {
    "word": "spare",
    "appLevel": "C1",
    "oxfordLevel": "B2"
  },
  {
    "word": "whoever",
    "appLevel": "C1",
    "oxfordLevel": "B2"
  },
  {
    "word": "workforce",
    "appLevel": "C1",
    "oxfordLevel": "B2"
  },
  {
    "word": "workplace",
    "appLevel": "C1",
    "oxfordLevel": "B2"
  }
]