{
  "id": "lsn_b2_j",
  "levelId": "lvl_b2",
  "title": "Unit 29: J Words",
  "slug": "j-words",
  "order": 29,
  "wordCount": 10,
  "titleAr": "الوحدة 29: كلمات حرف J",
  "description": "Master essential B2 vocabulary starting with the letter J.",
  "descriptionAr": "طور حصيلتك اللغوية في المستوى B2 مع كلمات تبدأ بحرف J.",
  "words": [
    {
      "id": "w_b2_jail",
      "en": "jail",
      "ar": "سجن / حبس",
      "lessonId": "lsn_b2_j",
      "levelId": "lvl_b2",
      "examples": [
        {
          "en": "The criminal escaped from jail last night.",
          "ar": "هرب المجرم من السجن الليلة الماضية."
        },
        {
          "en": "The judge decided to jail the thieves.",
          "ar": "قرر القاضي حبس اللصوص."
        }
      ],
      "type": "word",
      "difficulty": "B2",
      "tags": [
        "B2",
        "advanced"
      ],
      "confidence": "high",
      "needsTranslationReview": false,
      "ipa": "/dʒeɪl/"
    },
    {
      "id": "w_b2_jet",
      "en": "jet",
      "ar": "الطائرة (النفاثة)",
      "pronunciation": "",
      "lessonId": "lsn_b2_j",
      "levelId": "lvl_b2",
      "examples": [
        {
          "en": "The passengers cheered as the pilot landed the jet perfectly.",
          "ar": "ابتهج الركاب عندما هبط الطيار بالطائرة بشكل مثالي."
        }
      ],
      "type": "word",
      "difficulty": "B2",
      "tags": [
        "B2",
        "advanced"
      ],
      "confidence": "high",
      "needsTranslationReview": false
    },
    {
      "id": "w_b2_joint",
      "en": "joint",
      "ar": "مشترك / مفصل",
      "pronunciation": "",
      "lessonId": "lsn_b2_j",
      "levelId": "lvl_b2",
      "examples": [
        {
          "en": "He has pain in his knee joint.",
          "ar": "يعاني من ألم في مفصل ركبته."
        },
        {
          "en": "The project was a joint effort between departments.",
          "ar": "كان المشروع جهداً مشتركاً بين الإدارات."
        }
      ],
      "type": "word",
      "difficulty": "B2",
      "tags": [
        "B2",
        "advanced"
      ],
      "confidence": "high",
      "needsTranslationReview": false
    },
    {
      "id": "w_b2_journalism",
      "en": "journalism",
      "ar": "الصحافة",
      "pronunciation": "",
      "lessonId": "lsn_b2_j",
      "levelId": "lvl_b2",
      "examples": [
        {
          "en": "She attended a conference on digital journalism.",
          "ar": "هي حضرت مؤتمراً حول الصحافة الرقمية."
        }
      ],
      "type": "word",
      "difficulty": "B2",
      "tags": [
        "B2",
        "advanced"
      ],
      "confidence": "high",
      "needsTranslationReview": false
    },
    {
      "id": "w_b2_joy",
      "en": "joy",
      "ar": "بالبهجة",
      "pronunciation": "",
      "lessonId": "lsn_b2_j",
      "levelId": "lvl_b2",
      "examples": [
        {
          "en": "The children's laughter filled the room with joy.",
          "ar": "ضحكات الأطفال ملأت الغرفة بالبهجة."
        }
      ],
      "type": "word",
      "difficulty": "B2",
      "tags": [
        "B2",
        "advanced"
      ],
      "confidence": "high",
      "needsTranslationReview": false
    },
    {
      "id": "w_b2_judgment",
      "en": "judgment",
      "ar": "حكم",
      "pronunciation": "",
      "lessonId": "lsn_b2_j",
      "levelId": "lvl_b2",
      "examples": [
        {
          "en": "The court will deliver its judgment tomorrow.",
          "ar": "سوف تصدر المحكمة حكمها غدًا."
        }
      ],
      "type": "word",
      "difficulty": "B2",
      "tags": [
        "B2",
        "advanced"
      ],
      "confidence": "high",
      "needsTranslationReview": false
    },
    {
      "id": "w_b2_junior",
      "en": "junior",
      "ar": "المبتدئون",
      "pronunciation": "",
      "lessonId": "lsn_b2_j",
      "levelId": "lvl_b2",
      "examples": [
        {
          "en": "The junior members of the team will meet soon.",
          "ar": "سيجتمع أعضاء الفريق المبتدئون قريباً."
        }
      ],
      "type": "word",
      "difficulty": "B2",
      "tags": [
        "B2",
        "advanced"
      ],
      "confidence": "high",
      "needsTranslationReview": false
    },
    {
      "id": "w_b2_jury",
      "en": "jury",
      "ar": "هيئة المحلفين",
      "pronunciation": "",
      "lessonId": "lsn_b2_j",
      "levelId": "lvl_b2",
      "examples": [
        {
          "en": "The judge thanked the jury for their service.",
          "ar": "شكر القاضي هيئة المحلفين على خدمتهم."
        }
      ],
      "type": "word",
      "difficulty": "B2",
      "tags": [
        "B2",
        "advanced"
      ],
      "confidence": "high",
      "needsTranslationReview": false
    },
    {
      "id": "w_b2_justice",
      "en": "justice",
      "ar": "العدالة",
      "pronunciation": "",
      "lessonId": "lsn_b2_j",
      "levelId": "lvl_b2",
      "examples": [
        {
          "en": "Education is key to social justice.",
          "ar": "التعليم هو أساس العدالة الاجتماعية."
        }
      ],
      "type": "word",
      "difficulty": "B2",
      "tags": [
        "B2",
        "advanced"
      ],
      "confidence": "high",
      "needsTranslationReview": false
    },
    {
      "id": "w_b2_justify",
      "en": "justify",
      "ar": "يبرر",
      "lessonId": "lsn_b2_j",
      "levelId": "lvl_b2",
      "examples": [
        {
          "en": "The author used a lot of data to justify his theory.",
          "ar": "استخدم المؤلف الكثير من البيانات ليبرر نظريته."
        }
      ],
      "type": "word",
      "difficulty": "B2",
      "tags": [
        "B2",
        "advanced"
      ],
      "confidence": "high",
      "needsTranslationReview": false,
      "ipa": "/ˈdʒʌstɪfaɪ/"
    }
  ]
}
